hn_sdk/__init__.py
hn_sdk/_version.py
hn_sdk/client/__init__.py
hn_sdk/client/util.py
hn_sdk/client/v0/__init__.py
hn_sdk/client/v0/client.py
hn_sdk/property/client.properties
hn_sdk/util/ConfigReader.py
hn_sdk/util/__init__.py
test_e2e/__init__.py
hn_sdk-0.1.1.dist-info/LICENSE
hn_sdk-0.1.1.dist-info/METADATA
hn_sdk-0.1.1.dist-info/WHEEL
hn_sdk-0.1.1.dist-info/top_level.txt
hn_sdk-0.1.1.dist-info/RECORD
